ashar_website_monitor/__init__.py
ashar_website_monitor/main.py
ashar_website_monitor-0.1.0.dist-info/METADATA
ashar_website_monitor-0.1.0.dist-info/WHEEL
ashar_website_monitor-0.1.0.dist-info/entry_points.txt
ashar_website_monitor-0.1.0.dist-info/top_level.txt
ashar_website_monitor-0.1.0.dist-info/RECORD
