Metadata-Version: 2.4
Name: ashar-website-monitor
Version: 0.1.0
Summary: A Python tool to periodically check website availability and content with structured logging.
Author-email: Ashar Mehmood <asharmehmood056@gmail.com>
License-Expression: MIT
Requires-Python: >=3.7
Requires-Dist: requests>=2.25.0
Requires-Dist: PyYAML>=5.3
Requires-Dist: schedule>=1.1.0
Requires-Dist: python-json-logger>=2.0.0
Requires-Dist: pytest>=7.0.0
Provides-Extra: dev
Requires-Dist: pytest>=7.0.0; extra == "dev"
